uvbrew/__init__.py
uvbrew/uvbrew.py
uvbrew-0.1.8.dist-info/licenses/LICENSE
uvbrew-0.1.8.dist-info/METADATA
uvbrew-0.1.8.dist-info/WHEEL
uvbrew-0.1.8.dist-info/entry_points.txt
uvbrew-0.1.8.dist-info/top_level.txt
uvbrew-0.1.8.dist-info/RECORD
